wiz_alilog/__init__.py
wiz_alilog/client.py
wiz_alilog-1.0.2.dist-info/METADATA
wiz_alilog-1.0.2.dist-info/WHEEL
wiz_alilog-1.0.2.dist-info/top_level.txt
wiz_alilog-1.0.2.dist-info/RECORD
